<?xml version="1.0" encoding="UTF-8"?>
<bio:treatment xmlns:bio="http://www.github.com/biosemantics" xmlns:xsi="http://www.w3.org/2001/XMLSchema-instance" xsi:schemaLocation="http://www.github.com/biosemantics https://raw.githubusercontent.com/biosemantics/schemas/master/semanticMarkupOutput.xsd">
  <meta>
    <source>
      <author>unknown</author>
      <date>unknown</date>
    </source>
    <processed_by>
      <processor>
        <date>2018/03/21 18:04:20</date>
        <software type="Semantic Markup" version="0.1.196-SNAPSHOT">CharaParser</software>
        <operator />
        <resource type="OTO Glossary" version="0.19">Plant</resource>
      </processor>
    </processed_by>
    <other_info_on_meta type="volume">2</other_info_on_meta>
  </meta>
  <taxon_identification status="ACCEPTED">
    <taxon_name authority="Willkomm in Willkomm &amp; Lange" date="unknown" rank="family">selaginellaceae</taxon_name>
    <taxon_name authority="Palisot de Beauvois" date="1805" rank="genus">selaginella</taxon_name>
    <taxon_name authority="Jermy" date="1986" rank="subgenus">tetragonostachys</taxon_name>
    <taxon_name authority="Weatherby" date="1943" rank="species">viridissima</taxon_name>
    <place_of_publication>
      <publication_title>J. Arnold Arbor.</publication_title>
      <place_in_publication>24: 326. 1943</place_in_publication>
    </place_of_publication>
    <taxon_hierarchy>family selaginellaceae;genus selaginella;subgenus tetragonostachys;species viridissima</taxon_hierarchy>
  </taxon_identification>
  <taxon_identification status="SYNONYM">
    <taxon_name authority="unknown" date="unknown" rank="genus">Selaginella</taxon_name>
    <taxon_name authority="Weatherby" date="unknown" rank="species">coryi</taxon_name>
    <taxon_hierarchy>genus Selaginella;species coryi;</taxon_hierarchy>
  </taxon_identification>
  <description type="morphology">
    <statement id="d0_s0">
      <text>Plants on rock, forming clumps or mounds.</text>
      <biological_entity id="o9124" name="plant" name_original="plants" src="d0_s0" type="structure" />
      <biological_entity id="o9125" name="rock" name_original="rock" src="d0_s0" type="structure" />
      <biological_entity id="o9126" name="clump" name_original="clumps" src="d0_s0" type="structure" />
      <biological_entity id="o9127" name="mound" name_original="mounds" src="d0_s0" type="structure" />
      <relation from="o9124" id="r2092" name="on" negation="false" src="d0_s0" to="o9125" />
      <relation from="o9124" id="r2093" name="forming" negation="false" src="d0_s0" to="o9126" />
      <relation from="o9124" id="r2094" name="forming" negation="false" src="d0_s0" to="o9127" />
    </statement>
    <statement id="d0_s1">
      <text>Stems radially symmetric, underground (rhizomatous) and aerial, not readily fragmenting, irregularly forked;</text>
      <biological_entity id="o9128" name="stem" name_original="stems" src="d0_s1" type="structure">
        <character is_modifier="false" modifier="radially" name="architecture_or_shape" src="d0_s1" value="symmetric" />
        <character is_modifier="false" name="location" src="d0_s1" value="underground" />
        <character is_modifier="false" name="location" src="d0_s1" value="aerial" />
        <character is_modifier="false" modifier="not readily; readily; irregularly" name="shape" src="d0_s1" value="forked" />
      </biological_entity>
    </statement>
    <statement id="d0_s2">
      <text>rhizomatous and aerial stems often with 1 branch arrested, budlike, tips straight;</text>
      <biological_entity id="o9129" name="stem" name_original="stems" src="d0_s2" type="structure">
        <character is_modifier="true" name="architecture" src="d0_s2" value="rhizomatous" />
        <character is_modifier="true" name="location" src="d0_s2" value="aerial" />
        <character is_modifier="false" name="architecture_or_shape" notes="" src="d0_s2" value="budlike" />
      </biological_entity>
      <biological_entity id="o9130" name="branch" name_original="branch" src="d0_s2" type="structure">
        <character is_modifier="true" name="quantity" src="d0_s2" value="1" />
      </biological_entity>
      <biological_entity id="o9131" name="tip" name_original="tips" src="d0_s2" type="structure">
        <character is_modifier="false" name="course" src="d0_s2" value="straight" />
      </biological_entity>
      <relation from="o9129" id="r2095" name="with" negation="false" src="d0_s2" to="o9130" />
    </statement>
    <statement id="d0_s3">
      <text>aerial stems mainly erect, seldom ascending, with budlike arrested branches throughout stem length.</text>
      <biological_entity id="o9132" name="stem" name_original="stems" src="d0_s3" type="structure">
        <character is_modifier="true" name="location" src="d0_s3" value="aerial" />
        <character is_modifier="false" modifier="mainly" name="orientation" src="d0_s3" value="erect" />
        <character is_modifier="false" modifier="seldom" name="orientation" src="d0_s3" value="ascending" />
      </biological_entity>
      <biological_entity id="o9133" name="branch" name_original="branches" src="d0_s3" type="structure">
        <character is_modifier="true" name="architecture_or_shape" src="d0_s3" value="budlike" />
      </biological_entity>
      <relation from="o9132" id="r2096" name="with" negation="false" src="d0_s3" to="o9133" />
    </statement>
    <statement id="d0_s4">
      <text>Rhizophores borne on upperside of stems, restricted to rhizomatous stems and lower 1/4 of aerial stems, 0.16-0.3 mm diam.</text>
      <biological_entity id="o9134" name="rhizophore" name_original="rhizophores" src="d0_s4" type="structure">
        <character is_modifier="false" name="position" src="d0_s4" value="lower" />
        <character constraint="of stems" constraintid="o9138" name="quantity" src="d0_s4" value="1/4" />
        <character char_type="range_value" from="0.16" from_unit="mm" name="diameter" notes="" src="d0_s4" to="0.3" to_unit="mm" />
      </biological_entity>
      <biological_entity id="o9135" name="upperside" name_original="upperside" src="d0_s4" type="structure" />
      <biological_entity id="o9136" name="stem" name_original="stems" src="d0_s4" type="structure" />
      <biological_entity id="o9137" name="stem" name_original="stems" src="d0_s4" type="structure">
        <character is_modifier="true" name="architecture" src="d0_s4" value="rhizomatous" />
      </biological_entity>
      <biological_entity id="o9138" name="stem" name_original="stems" src="d0_s4" type="structure">
        <character is_modifier="true" name="location" src="d0_s4" value="aerial" />
      </biological_entity>
      <relation from="o9134" id="r2097" name="borne on" negation="false" src="d0_s4" to="o9135" />
      <relation from="o9134" id="r2098" name="borne on" negation="false" src="d0_s4" to="o9136" />
      <relation from="o9134" id="r2099" name="restricted to" negation="false" src="d0_s4" to="o9137" />
    </statement>
    <statement id="d0_s5">
      <text>Leaves dimorphic, not clearly ranked.</text>
      <biological_entity id="o9139" name="leaf" name_original="leaves" src="d0_s5" type="structure">
        <character is_modifier="false" name="growth_form" src="d0_s5" value="dimorphic" />
        <character is_modifier="false" modifier="not clearly" name="arrangement" src="d0_s5" value="ranked" />
      </biological_entity>
    </statement>
    <statement id="d0_s6">
      <text>Rhizomatous stem-leaves loosely appressed, straight, scalelike.</text>
      <biological_entity id="o9140" name="stem-leaf" name_original="stem-leaves" src="d0_s6" type="structure">
        <character is_modifier="true" name="architecture" src="d0_s6" value="rhizomatous" />
        <character is_modifier="false" modifier="loosely" name="fixation_or_orientation" src="d0_s6" value="appressed" />
        <character is_modifier="false" name="course" src="d0_s6" value="straight" />
        <character is_modifier="false" name="shape" src="d0_s6" value="scale-like" value_original="scalelike" />
      </biological_entity>
    </statement>
    <statement id="d0_s7">
      <text>Aerial stem-leaves appressed, ascending, green, linear-lanceolate to narrowly lanceolate, 1.8-2.1 X 0.49-0.56 mm;</text>
      <biological_entity id="o9141" name="stem-leaf" name_original="stem-leaves" src="d0_s7" type="structure">
        <character is_modifier="true" name="location" src="d0_s7" value="aerial" />
        <character is_modifier="false" name="fixation_or_orientation" src="d0_s7" value="appressed" />
        <character is_modifier="false" name="orientation" src="d0_s7" value="ascending" />
        <character is_modifier="false" name="coloration" src="d0_s7" value="green" />
        <character is_modifier="false" name="shape" notes="[duplicate value]" src="d0_s7" value="linear-lanceolate" />
        <character is_modifier="false" modifier="narrowly" name="shape" notes="[duplicate value]" src="d0_s7" value="lanceolate" />
        <character char_type="range_value" from="linear-lanceolate" name="shape" src="d0_s7" to="narrowly lanceolate" />
        <character char_type="range_value" from="1.8" from_unit="mm" name="length" src="d0_s7" to="2.1" to_unit="mm" />
        <character char_type="range_value" from="0.49" from_unit="mm" name="width" src="d0_s7" to="0.56" to_unit="mm" />
      </biological_entity>
    </statement>
    <statement id="d0_s8">
      <text>abaxial ridges prominent;</text>
      <biological_entity constraint="abaxial" id="o9142" name="ridge" name_original="ridges" src="d0_s8" type="structure">
        <character is_modifier="false" name="prominence" src="d0_s8" value="prominent" />
      </biological_entity>
    </statement>
    <statement id="d0_s9">
      <text>base cuneate and decurrent to slightly rounded and adnate, glabrous;</text>
      <biological_entity id="o9143" name="base" name_original="base" src="d0_s9" type="structure">
        <character is_modifier="false" name="shape" src="d0_s9" value="cuneate" />
        <character is_modifier="false" name="shape" notes="[duplicate value]" src="d0_s9" value="decurrent" />
        <character is_modifier="false" modifier="slightly" name="shape" notes="[duplicate value]" src="d0_s9" value="rounded" />
        <character char_type="range_value" from="decurrent" name="shape" src="d0_s9" to="slightly rounded" />
        <character is_modifier="false" name="fusion" src="d0_s9" value="adnate" />
        <character is_modifier="false" name="pubescence" src="d0_s9" value="glabrous" />
      </biological_entity>
    </statement>
    <statement id="d0_s10">
      <text>margins denticulate to very short-ciliate, cilia transparent, spreading to ascending toward apex, 0.02-0.04 mm;</text>
      <biological_entity id="o9144" name="margin" name_original="margins" src="d0_s10" type="structure">
        <character is_modifier="false" name="shape" src="d0_s10" value="denticulate to very" />
        <character is_modifier="false" modifier="very" name="architecture_or_pubescence_or_shape" src="d0_s10" value="short-ciliate" />
      </biological_entity>
      <biological_entity id="o9145" name="cilium" name_original="cilia" src="d0_s10" type="structure">
        <character is_modifier="false" name="coloration" src="d0_s10" value="transparent" />
        <character is_modifier="false" name="orientation" notes="[duplicate value]" src="d0_s10" value="spreading" />
        <character is_modifier="false" name="orientation" notes="[duplicate value]" src="d0_s10" value="ascending" />
        <character char_type="range_value" constraint="toward apex" constraintid="o9146" from="spreading" name="orientation" src="d0_s10" to="ascending" />
        <character char_type="range_value" from="0.02" from_unit="mm" name="some_measurement" notes="" src="d0_s10" to="0.04" to_unit="mm" />
      </biological_entity>
      <biological_entity id="o9146" name="apex" name_original="apex" src="d0_s10" type="structure" />
    </statement>
    <statement id="d0_s11">
      <text>apex acute or seldom blunt.</text>
      <biological_entity id="o9147" name="apex" name_original="apex" src="d0_s11" type="structure">
        <character is_modifier="false" name="shape" src="d0_s11" value="acute" />
        <character is_modifier="false" modifier="seldom" name="shape" src="d0_s11" value="blunt" />
      </biological_entity>
    </statement>
    <statement id="d0_s12">
      <text>Strobili solitary, 0.5-1.2 (-2.5) cm;</text>
      <biological_entity id="o9148" name="strobilus" name_original="strobili" src="d0_s12" type="structure">
        <character is_modifier="false" name="architecture_or_arrangement_or_growth_form" src="d0_s12" value="solitary" />
        <character char_type="range_value" from="1.2" from_inclusive="false" from_unit="cm" name="atypical_some_measurement" src="d0_s12" to="2.5" to_unit="cm" />
        <character char_type="range_value" from="0.5" from_unit="cm" name="some_measurement" src="d0_s12" to="1.2" to_unit="cm" />
      </biological_entity>
    </statement>
    <statement id="d0_s13">
      <text>sporophylls deltate-ovate to ovatelanceolate, abaxial ridges prominent, base glabrous, margins denticulate, apex acute to obtuse.</text>
      <biological_entity id="o9149" name="sporophyll" name_original="sporophylls" src="d0_s13" type="structure">
        <character is_modifier="false" name="shape" notes="[duplicate value]" src="d0_s13" value="deltate-ovate" />
        <character is_modifier="false" name="shape" notes="[duplicate value]" src="d0_s13" value="ovatelanceolate" />
        <character char_type="range_value" from="deltate-ovate" name="shape" src="d0_s13" to="ovatelanceolate" />
      </biological_entity>
      <biological_entity constraint="abaxial" id="o9150" name="ridge" name_original="ridges" src="d0_s13" type="structure">
        <character is_modifier="false" name="prominence" src="d0_s13" value="prominent" />
      </biological_entity>
      <biological_entity id="o9151" name="base" name_original="base" src="d0_s13" type="structure">
        <character is_modifier="false" name="pubescence" src="d0_s13" value="glabrous" />
      </biological_entity>
      <biological_entity id="o9152" name="margin" name_original="margins" src="d0_s13" type="structure">
        <character is_modifier="false" name="shape" src="d0_s13" value="denticulate" />
      </biological_entity>
      <biological_entity id="o9153" name="apex" name_original="apex" src="d0_s13" type="structure">
        <character is_modifier="false" name="shape" notes="[duplicate value]" src="d0_s13" value="acute" />
        <character is_modifier="false" name="shape" notes="[duplicate value]" src="d0_s13" value="obtuse" />
        <character char_type="range_value" from="acute" name="shape" src="d0_s13" to="obtuse" />
      </biological_entity>
    </statement>
  </description>
  <description type="habitat">
    <statement id="habitat_0">
      <text>Shaded cliffs, slopes, rock crevices, and igneous rock;</text>
      <biological_entity id="hab_o0" name="whole_organism" name_original="" type="structure">
        <character name="habitat" value="shaded cliffs" />
        <character name="habitat" value="slopes" />
        <character name="habitat" value="rock crevices" />
      </biological_entity>
    </statement>
  </description>
  <description type="elevation">
    <statement id="elevation_0">
      <text>1650--2300 m;</text>
      <biological_entity id="elev_o0" name="whole_organism" name_original="" type="structure">
        <character name="elevation" char_type="range_value" to="2300" to_unit="m" from="1650" from_unit="m" />
      </biological_entity>
    </statement>
  </description>
  <description type="distribution">
    <statement id="distribution_0">
      <text>Tex.; Mexico in Coahuila.</text>
      <biological_entity id="dis_o0" name="whole_organism" name_original="" type="structure">
        <character name="distribution" geographical_constraint="United States" value="Tex." establishment_means="native" />
        <character name="distribution" value="Mexico in Coahuila" establishment_means="native" />
      </biological_entity>
    </statement>
  </description>
  <number>11</number>
  <other_name type="common_name">Slender spike-moss</other_name>
  <discussion>In Texas Selaginella viridissima is known only from the Chisos Mountains.</discussion>
  <discussion type="conservation">of conservation concern</discussion>
</bio:treatment>
